kamasi/__init__.py
kamasi/audio_processing.py
kamasi/cli.py
kamasi/llm_refinement.py
kamasi/transcription.py
kamasi-0.1.1.dist-info/METADATA
kamasi-0.1.1.dist-info/WHEEL
kamasi-0.1.1.dist-info/entry_points.txt
kamasi-0.1.1.dist-info/licenses/LICENSE
kamasi-0.1.1.dist-info/RECORD
