Metadata-Version: 2.4
Name: kamasi
Version: 0.1.1
Summary: Music lyrics transcription tool using AI
License-Expression: MIT
License-File: LICENSE
Requires-Python: <3.14,>=3.13
Requires-Dist: demucs>=4.0.1
Requires-Dist: faster-whisper>=1.2.1
Requires-Dist: loguru>=0.7.3
Requires-Dist: ollama>=0.6.1
Requires-Dist: pyyaml>=6.0.3
Requires-Dist: torchaudio>=2.9.1
Requires-Dist: torchcodec>=0.9.1
Requires-Dist: typer>=0.20.1
